nextlog/__init__.py
nextlog/logger.py
nextlog-2.0.1.dist-info/LICENSE
nextlog-2.0.1.dist-info/METADATA
nextlog-2.0.1.dist-info/WHEEL
nextlog-2.0.1.dist-info/top_level.txt
nextlog-2.0.1.dist-info/RECORD
