Metadata-Version: 2.1
Name: nextlog
Version: 2.0.1
Summary: A logging library with asynchronous logs dispatch to Loki.
Home-page: https://github.com/sourav-py/nextlog
Author: Sourav
Author-email: imsrv2k@gmail.com
License-File: LICENSE
Requires-Dist: requests
Requires-Dist: redis
